{
  "channel": "SINOSOURCING",
  "videos": [
    {
      "file": "dPncDtMDBhA.txt",
      "title": "He equips his restaurants using Chinese products",
      "chars": 8609
    },
    {
      "file": "k7iCyvLmS30.txt",
      "title": "Capsule House in China: Factory Tour",
      "chars": 25968
    },
    {
      "file": "LZgrp9U6qUA.txt",
      "title": "These Chinese machines cost LESS than a salary",
      "chars": 19433
    },
    {
      "file": "4wIUebP8Ols.txt",
      "title": "Inside a Factory in China: Spa and Sauna",
      "chars": 18416
    },
    {
      "file": "9CYhDmbvw0g.txt",
      "title": "Creating your brand in China",
      "chars": 6494
    },
    {
      "file": "53Q2rEOWNMQ.txt",
      "title": "Buying in China: Is it worth it in 2025",
      "chars": 6959
    },
    {
      "file": "mJteTopF_hE.txt",
      "title": "They resell snack equipment imported from China",
      "chars": 16897
    },
    {
      "file": "qTlX99mYZ2I.txt",
      "title": "Goods stuck in customs, lost, broken: Who is responsible",
      "chars": 11950
    },
    {
      "file": "vLtUHRijizk.txt",
      "title": "At 22 he imported a container to furnish 15 apartments",
      "chars": 17329
    },
    {
      "file": "n_rxim8Ku2E.txt",
      "title": "Spa Factory in China: Real Factory Prices",
      "chars": 21204
    },
    {
      "file": "VV4t5bfua6k.txt",
      "title": "Canton Fair Phase 2: Import Strategies",
      "chars": 25948
    },
    {
      "file": "yDQIx8eAf1w.txt",
      "title": "The Sea Cartel: What your freight forwarder will never tell you",
      "chars": 5118
    },
    {
      "file": "DDn-XRzcd2s.txt",
      "title": "He imported an ENTIRE gym from China",
      "chars": 15789
    },
    {
      "file": "dS4NXYhw_j0.txt",
      "title": "The Chinese factory that will kill the construction industry",
      "chars": 16981
    },
    {
      "file": "6Nfqqy41Ql8.txt",
      "title": "Il importe un Food Truck sur-mesure de Chine",
      "chars": 15471
    }
  ],
  "total_content_chars": 232566
}